beta_solver/__init__.py
beta_solver/linear_regression.py
beta_solver/logistic_regression.py
beta_solver-0.0.2.dist-info/licenses/LICENSE
beta_solver-0.0.2.dist-info/METADATA
beta_solver-0.0.2.dist-info/WHEEL
beta_solver-0.0.2.dist-info/top_level.txt
beta_solver-0.0.2.dist-info/RECORD
