Metadata-Version: 2.4
Name: beta_solver
Version: 0.0.2
Summary: A transparent, pure-math implementation of Multiple Linear Regression using the Normal Equation.
Author-email: Abhish Bondre <abhishbondre232@gmail.com>
Project-URL: Homepage, https://github.com/abhishbondre/beta_solver
Classifier: Programming Language :: Python :: 3
Classifier: License :: OSI Approved :: MIT License
Classifier: Operating System :: OS Independent
Classifier: Topic :: Scientific/Engineering :: Mathematics
Classifier: Intended Audience :: Education
Requires-Python: >=3.7
License-File: LICENSE
Requires-Dist: numpy
Dynamic: license-file
